wexample_app-0.0.71.dist-info/METADATA
wexample_app-0.0.71.dist-info/WHEEL
wexample_app-0.0.71.dist-info/entry_points.txt
wexample_app/__init__.py
wexample_app/__pycache__/__init__.py
wexample_app/command/__init__.py
wexample_app/command/__pycache__/__init__.py
wexample_app/command/option.py
wexample_app/common/__init__.py
wexample_app/common/__pycache__/__init__.py
wexample_app/common/abstract_kernel.py
wexample_app/common/abstract_kernel_child.py
wexample_app/common/command.py
wexample_app/common/command_request.py
wexample_app/common/mixins/__init__.py
wexample_app/common/mixins/__pycache__/__init__.py
wexample_app/common/mixins/command_line_kernel.py
wexample_app/common/mixins/command_runner_kernel.py
wexample_app/common/protocol/__init__.py
wexample_app/common/service/__init__.py
wexample_app/common/service/__pycache__/__init__.py
wexample_app/common/service/service_mixin.py
wexample_app/const/__init__.py
wexample_app/const/__pycache__/__init__.py
wexample_app/const/env.py
wexample_app/const/globals.py
wexample_app/const/output.py
wexample_app/const/path.py
wexample_app/const/registries.py
wexample_app/const/types.py
wexample_app/exception/__init__.py
wexample_app/exception/__pycache__/__init__.py
wexample_app/exception/app_runtime_exception.py
wexample_app/exception/command_argument_conversion_exception.py
wexample_app/exception/command_build_failed_exception.py
wexample_app/exception/command_function_name_missing_exception.py
wexample_app/exception/command_function_not_found_exception.py
wexample_app/exception/command_module_load_error_exception.py
wexample_app/exception/command_resolver_not_found_exception.py
wexample_app/exception/command_runner_missing_exception.py
wexample_app/exception/command_runner_not_found_exception.py
wexample_app/exception/command_type_not_found_exception.py
wexample_app/exception/command_unexpected_argument_exception.py
wexample_app/exception/exception_data.py
wexample_app/exception/response_invalid_content_type_exception.py
wexample_app/helpers/__init__.py
wexample_app/helpers/__pycache__/__init__.py
wexample_app/helpers/argument.py
wexample_app-0.0.71.dist-info/RECORD
