Metadata-Version: 2.1
Name: wexample-app
Version: 0.0.71
Summary: Helpers for building Python app or cli.
Author-Email: weeger <contact@wexample.com>
License: MIT
Classifier: Programming Language :: Python :: 3
Classifier: License :: OSI Approved :: MIT License
Classifier: Operating System :: OS Independent
Project-URL: homepage, https://github.com/wexample/python-app
Requires-Python: >=3.10
Requires-Dist: attrs>=23.1.0
Requires-Dist: cattrs>=23.1.0
Requires-Dist: dotenv
Requires-Dist: python-dotenv
Requires-Dist: wexample-filestate==0.0.74
Requires-Dist: wexample-helpers-yaml==0.0.113
Provides-Extra: dev
Requires-Dist: pytest; extra == "dev"
Requires-Dist: pytest-cov; extra == "dev"
